{"global_attributes": {"file_id": "X51007103692.jpg"}, "fields": [{"field_name": "company", "key_id": [], "key_text": [], "value_id": [1], "value_text": ["MR. D.I.Y. (M) SDN BHD"]}, {"field_name": "date", "key_id": [], "key_text": [], "value_id": [2], "value_text": ["28-04-18"]}, {"field_name": "address", "key_id": [], "key_text": [], "value_id": [3, 4, 5], "value_text": ["LOT 1851-A & 1851-B, JALAN KPB 6,", "KAWASAN PERINDUSTRIAN BALAKONG,", "43300 SERI KEMBANGAN, SELANGOR"]}, {"field_name": "total", "key_id": [], "key_text": [], "value_id": [6], "value_text": ["53.20"]}], "text_boxes": [{"id": 1, "bbox": [547, 180, 327, 295], "text": "MR. D.I.Y. (M) SDN BHD"}, {"id": 2, "bbox": [167, 31, 1197, 1166], "text": "28-04-18"}, {"id": 3, "bbox": [627, 82, 397, 363], "text": "LOT 1851-A & 1851-B, JALAN KPB 6,"}, {"id": 4, "bbox": [608, 97, 429, 396], "text": "KAWASAN PERINDUSTRIAN BALAKONG,"}, {"id": 5, "bbox": [615, 114, 463, 430], "text": "43300 SERI KEMBANGAN, SELANGOR"}, {"id": 6, "bbox": [696, 563, 995, 967], "text": "53.20"}]}