{"global_attributes": {"file_id": "X51006392313.jpg"}, "fields": [{"field_name": "company", "key_id": [], "key_text": [], "value_id": [1], "value_text": ["SUPER.SEVEN CASH & CARRY SDN BHD"]}, {"field_name": "date", "key_id": [], "key_text": [], "value_id": [2], "value_text": ["22-06-2017"]}, {"field_name": "address", "key_id": [], "key_text": [], "value_id": [3, 4, 5], "value_text": ["NO. 1 JALAN EURO 1", "OFF JALAN BATU TIGA", "SUNGAI BULOH SEKSYEN U3 SHAH ALAM,40150"]}, {"field_name": "total", "key_id": [], "key_text": [], "value_id": [6], "value_text": ["RM28.05"]}], "text_boxes": [{"id": 1, "bbox": [476, 19, 157, 129], "text": "SUPER.SEVEN CASH & CARRY SDN BHD"}, {"id": 2, "bbox": [165, 21, 726, 694], "text": "22-06-2017"}, {"id": 3, "bbox": [275, 19, 263, 235], "text": "NO. 1 JALAN EURO 1"}, {"id": 4, "bbox": [292, 18, 303, 270], "text": "OFF JALAN BATU TIGA"}, {"id": 5, "bbox": [573, 16, 338, 307], "text": "SUNGAI BULOH SEKSYEN U3 SHAH ALAM,40150"}, {"id": 6, "bbox": [588, 488, 1283, 1255], "text": "RM28.05"}]}